dataflow/__init__.py
dataflow/cli.py
dataflow/logger.py
dataflow/version.py
dataflow/cli_funcs/__init__.py
dataflow/cli_funcs/cli_env.py
dataflow/cli_funcs/cli_eval.py
dataflow/cli_funcs/cli_init.py
dataflow/cli_funcs/cli_pdf.py
dataflow/cli_funcs/cli_text.py
dataflow/cli_funcs/copy_funcs.py
dataflow/cli_funcs/paths.py
dataflow/cli_funcs/eval_pipeline/eval_api.py
dataflow/cli_funcs/eval_pipeline/eval_local.py
dataflow/cli_funcs/pdf2model_pipeline/llama_factory_trainer.py
dataflow/cli_funcs/pdf2model_pipeline/path_to_jsonl_script.py
dataflow/cli_funcs/pdf2model_pipeline/pdf_to_qa_pipeline.py
dataflow/cli_funcs/text2model_pipeline/llama_factory_trainer.py
dataflow/cli_funcs/text2model_pipeline/merge_filter_qa_pairs.py
dataflow/cli_funcs/text2model_pipeline/text_to_qa_pipeline.py
dataflow/core/__init__.py
dataflow/core/llm_serving.py
dataflow/core/operator.py
dataflow/core/prompt.py
dataflow/core/wrapper.py
dataflow/example/AgenticRAGPipeline/eval_test_data.jsonl
dataflow/example/CodePipeline/code_input.jsonl
dataflow/example/CodePipeline/code_synthesis_input.jsonl
dataflow/example/CodePipeline/raw_code.jsonl
dataflow/example/DataflowAgent/agent_test_data.json
dataflow/example/DataflowAgent/mq_test_data.jsonl
dataflow/example/FuncCallPipeline/chat_data.jsonl
dataflow/example/GeneralTextPipeline/abbreviation.jsonl
dataflow/example/GeneralTextPipeline/filtering.json
dataflow/example/GeneralTextPipeline/gen_input.jsonl
dataflow/example/GeneralTextPipeline/math_100.jsonl
dataflow/example/GeneralTextPipeline/pandas.json
dataflow/example/GeneralTextPipeline/pt_input.jsonl
dataflow/example/GeneralTextPipeline/sft_input.jsonl
dataflow/example/GeneralTextPipeline/translation.jsonl
dataflow/example/KBCleaningPipeline/bitter_lesson.pdf
dataflow/example/KBCleaningPipeline/kbc_placeholder.json
dataflow/example/KBCleaningPipeline/kbc_playground.jsonl
dataflow/example/KBCleaningPipeline/kbc_test.jsonl
dataflow/example/KBCleaningPipeline/kbc_test_1.jsonl
open_dataflow-1.0.8.dist-info/licenses/LICENSE
open_dataflow-1.0.8.dist-info/METADATA
open_dataflow-1.0.8.dist-info/WHEEL
open_dataflow-1.0.8.dist-info/entry_points.txt
open_dataflow-1.0.8.dist-info/top_level.txt
open_dataflow-1.0.8.dist-info/RECORD
