Metadata-Version: 2.4
Name: open-dataflow
Version: 1.0.8
Summary: Modern Data Centric AI system for Large Language Models
Author-email: Hao Liang <hao.liang@stu.pku.edu.cn>, Xiaochen Ma <xiaochen.ma.cs@gmail.com>
License: Apache-2.0
Project-URL: Github, https://github.com/Open-DataFlow/DataFlow
Project-URL: Documentation, https://open-dataflow.github.io/DataFlow-Doc/
Project-URL: Bug Reports, https://github.com/Open-DataFlow/DataFlow/issues
Keywords: AI,artificial intelligence
Classifier: Development Status :: 3 - Alpha
Classifier: Intended Audience :: Developers
Classifier: Intended Audience :: Science/Research
Classifier: Topic :: Scientific/Engineering :: Artificial Intelligence
Classifier: License :: Free For Educational Use
Classifier: Programming Language :: Python :: 3
Classifier: Programming Language :: Python :: 3.10
Classifier: Programming Language :: Python :: 3.11
Classifier: Programming Language :: Python :: 3.12
Classifier: Programming Language :: Python :: 3 :: Only
Requires-Python: <4,>=3.7
License-File: LICENSE
Requires-Dist: numpy<2.0.0
Requires-Dist: datasets
Requires-Dist: scipy
Requires-Dist: torch
Requires-Dist: torchvision
Requires-Dist: torchaudio
Requires-Dist: tqdm
Requires-Dist: transformers
Requires-Dist: math_verify
Requires-Dist: word2number
Requires-Dist: accelerate
Requires-Dist: rapidfuzz
Requires-Dist: colorlog
Requires-Dist: appdirs
Requires-Dist: datasketch
Requires-Dist: modelscope
Requires-Dist: addict
Requires-Dist: pytest
Requires-Dist: rich
Requires-Dist: docstring_parser
Requires-Dist: pydantic
Requires-Dist: nltk
Requires-Dist: colorama
Requires-Dist: gradio>5
Requires-Dist: json5
Requires-Dist: tiktoken
Requires-Dist: pyarrow==20.0.0
Requires-Dist: func_timeout
Requires-Dist: sqlglot
Requires-Dist: pymysql
Requires-Dist: fasttext-wheel
Requires-Dist: langkit
Requires-Dist: openai
Requires-Dist: sentencepiece
Requires-Dist: datasketch
Requires-Dist: presidio_analyzer[transformers]
Requires-Dist: presidio_anonymizer
Requires-Dist: vendi-score==0.0.3
Requires-Dist: google-api-core
Requires-Dist: google-api-python-client
Requires-Dist: evaluate
Requires-Dist: contractions
Requires-Dist: symspellpy
Requires-Dist: simhash
Requires-Dist: chonkie
Requires-Dist: trafilatura
Requires-Dist: lxml_html_clean
Requires-Dist: pymupdf
Requires-Dist: httpx[socks]
Requires-Dist: cloudpickle
Requires-Dist: fastapi
Requires-Dist: httpx
Requires-Dist: pandas
Requires-Dist: psutil
Requires-Dist: pyfiglet
Requires-Dist: pyyaml
Requires-Dist: requests
Requires-Dist: termcolor
Requires-Dist: uvicorn
Requires-Dist: sseclient-py
Requires-Dist: librosa
Requires-Dist: soundfile
Requires-Dist: google-cloud-aiplatform>=1.55
Requires-Dist: google-cloud-bigquery
Requires-Dist: google-genai
Requires-Dist: gcsfs
Requires-Dist: db-dtypes
Requires-Dist: google-cloud-bigquery-storage
Provides-Extra: vllm
Requires-Dist: vllm<=0.9.2,>=0.7.0; extra == "vllm"
Requires-Dist: numpy<2.0.0; extra == "vllm"
Provides-Extra: vllm07
Requires-Dist: vllm<0.8; extra == "vllm07"
Requires-Dist: numpy<2.0.0; extra == "vllm07"
Provides-Extra: vllm08
Requires-Dist: vllm<0.9; extra == "vllm08"
Provides-Extra: kbc
Requires-Dist: vllm==0.6.3; extra == "kbc"
Requires-Dist: mineru[pipeline]==2.0.6; extra == "kbc"
Provides-Extra: mineru
Requires-Dist: mineru[all]; extra == "mineru"
Requires-Dist: numpy<2.0.0,>=1.24; extra == "mineru"
Requires-Dist: sglang[all]>=0.4.8; extra == "mineru"
Requires-Dist: pypdf; extra == "mineru"
Requires-Dist: reportlab; extra == "mineru"
Provides-Extra: myscale
Requires-Dist: clickhouse-driver; extra == "myscale"
Provides-Extra: sglang
Requires-Dist: sglang[all]; extra == "sglang"
Provides-Extra: litellm
Requires-Dist: litellm<2.0.0,>=1.70.0; extra == "litellm"
Provides-Extra: audio
Requires-Dist: librosa; extra == "audio"
Requires-Dist: soundfile; extra == "audio"
Provides-Extra: vectorsql
Requires-Dist: sqlite-vec; extra == "vectorsql"
Requires-Dist: sqlite-lembed; extra == "vectorsql"
Requires-Dist: sentence_transformers; extra == "vectorsql"
Provides-Extra: pdf2model
Requires-Dist: llamafactory[metrics,torch]>=0.9.0; extra == "pdf2model"
Requires-Dist: vllm<0.9.2,>=0.7.0; extra == "pdf2model"
Requires-Dist: numpy<2.0.0,>=1.24; extra == "pdf2model"
Requires-Dist: mineru[pipeline]; extra == "pdf2model"
Requires-Dist: mineru-vl-utils; extra == "pdf2model"
Provides-Extra: eval
Requires-Dist: vllm<0.9.2,>=0.7.0; extra == "eval"
Provides-Extra: rag
Requires-Dist: lightrag-hku; extra == "rag"
Requires-Dist: asyncio; extra == "rag"
Dynamic: license-file
